ninety/__init__.py
ninety/codegen/__init__.py
ninety/codegen/config.py
ninety/codegen/generators.py
ninety/codegen/pipeline.py
ninety/codegen/utils.py
ninety/codegen/validators.py
ninety-0.1.8.dist-info/METADATA
ninety-0.1.8.dist-info/WHEEL
ninety-0.1.8.dist-info/top_level.txt
ninety-0.1.8.dist-info/RECORD
